py_spirentaion_rest_client/SpirentAion.py
py_spirentaion_rest_client/__init__.py
py_spirentaion_rest_client-0.2.dist-info/LICENSE
py_spirentaion_rest_client-0.2.dist-info/METADATA
py_spirentaion_rest_client-0.2.dist-info/WHEEL
py_spirentaion_rest_client-0.2.dist-info/top_level.txt
py_spirentaion_rest_client-0.2.dist-info/zip-safe
py_spirentaion_rest_client-0.2.dist-info/RECORD
